haco/__init__.py
haco/base.py
haco/binary_sensor.py
haco/button.py
haco/capabilities.py
haco/client.py
haco/climate.py
haco/constants.py
haco/control.py
haco/device.py
haco/number.py
haco/obs.py
haco/paths.py
haco/project.py
haco/sb3.py
haco/select.py
haco/sensor.py
haco/switch.py
haco/text.py
haco/topics.py
haco/uom.py
haco/utils.py
haco/version
haco/version.py
haco-0.1.9.dist-info/METADATA
haco-0.1.9.dist-info/WHEEL
haco-0.1.9.dist-info/top_level.txt
haco-0.1.9.dist-info/RECORD
