Metadata-Version: 2.4
Name: haco
Version: 0.1.9
Summary: Home Assistant Control Objects
Home-page: https://github.com/None/haco
Author: Frontmatter
Author-email: innovative.fowler@mask.pro.fmtr.dev
License: Copyright © 2026 Frontmatter. All rights reserved.
Keywords: homeassistant controls python tasmota
Requires-Dist: fmtr.tools[api,caching,debug,logging,mqtt,sets,version.dev,yaml]
Provides-Extra: all
Dynamic: author
Dynamic: author-email
Dynamic: description
Dynamic: description-content-type
Dynamic: home-page
Dynamic: keywords
Dynamic: license
Dynamic: provides-extra
Dynamic: requires-dist
Dynamic: summary
